autodistill_detr/__init__.py
autodistill_detr/detr_model.py
src/__init__.py
src/hello.py
autodistill_detr-0.1.1.dist-info/LICENSE
autodistill_detr-0.1.1.dist-info/METADATA
autodistill_detr-0.1.1.dist-info/WHEEL
autodistill_detr-0.1.1.dist-info/top_level.txt
autodistill_detr-0.1.1.dist-info/RECORD
