Metadata-Version: 2.1
Name: autodistill-detr
Version: 0.1.1
Summary: DETR module for use with Autodistill
Home-page: https://github.com/autodistill/autodistill-detr
Author: Roboflow
Author-email: support@roboflow.com
Classifier: Programming Language :: Python :: 3
Classifier: License :: OSI Approved :: MIT License
Classifier: Operating System :: OS Independent
Requires-Python: >=3.7
License-File: LICENSE
Requires-Dist: supervision ==0.9.0
Requires-Dist: transformers
Requires-Dist: torch
Requires-Dist: numpy
Requires-Dist: Pillow
Requires-Dist: autodistill
Requires-Dist: timm
Requires-Dist: pytorch-lightning
Requires-Dist: torchvision
Provides-Extra: dev
Requires-Dist: flake8 ; extra == 'dev'
Requires-Dist: black ==22.3.0 ; extra == 'dev'
Requires-Dist: isort ; extra == 'dev'
Requires-Dist: twine ; extra == 'dev'
Requires-Dist: pytest ; extra == 'dev'
Requires-Dist: wheel ; extra == 'dev'
